CHANGES.txt
MANIFEST.in
README.rst
setup.py
pyramid_versionbadge/__init__.py
pyramid_versionbadge/tests.py
pyramid_versionbadge.egg-info/PKG-INFO
pyramid_versionbadge.egg-info/SOURCES.txt
pyramid_versionbadge.egg-info/dependency_links.txt
pyramid_versionbadge.egg-info/not-zip-safe
pyramid_versionbadge.egg-info/requires.txt
pyramid_versionbadge.egg-info/top_level.txt