Metadata-Version: 1.1
Name: pyramid-versionbadge
Version: 0.3
Summary: A tween which renders a badge on the page indicating the version.
Home-page: http://www.gocept.com
Author: Daniel Havlik
Author-email: dh@gocept.com
License: BSD
Keywords: wsgi pylons pyramid staging production testing
Platform: UNKNOWN
Classifier: Intended Audience :: Developers
Classifier: Programming Language :: Python
Classifier: Programming Language :: Python :: 3.4
Classifier: Programming Language :: Python :: 3.5
Classifier: Programming Language :: Python :: 3.6
Classifier: Programming Language :: Python :: 3.7
Classifier: Framework :: Pyramid
Classifier: Topic :: Internet :: WWW/HTTP :: WSGI
Classifier: License :: Repoze Public License
